sciphi/__init__.py
sciphi/config/__init__.py
sciphi/config/generation_settings/textbook_generation_settings.yaml
sciphi/config/prompts/chain_of_thought.yaml
sciphi/config/prompts/question_and_answer.yaml
sciphi/core/__init__.py
sciphi/core/base.py
sciphi/core/prompt/__init__.py
sciphi/core/prompt/base.py
sciphi/core/utils.py
sciphi/core/writers/__init__.py
sciphi/core/writers/base.py
sciphi/core/writers/jsonl_writer.py
sciphi/core/writers/raw_writer.py
sciphi/data/evals/science_multiple_choice.csv
sciphi/data/sample/table_of_contents/Aerodynamics_of_Viscous_Fluids.yaml
sciphi/data/sample/textbooks/Aerodynamics_of_Viscous_Fluids.md
sciphi/deprecated/basic_data_gen/__init__.py
sciphi/deprecated/basic_data_gen/runner.py
sciphi/deprecated/khan_academy/__init__.py
sciphi/deprecated/khan_academy/gen_step_1_draft_syllabi.py
sciphi/deprecated/khan_academy/gen_step_2_draft_table_of_contents.py
sciphi/deprecated/khan_academy/generate_textbook.py
sciphi/deprecated/khan_academy/prompts.py
sciphi/deprecated/khan_academy/raw_data/ka_courses.html
sciphi/deprecated/khan_academy/raw_data/ka_scraped.jsonl
sciphi/deprecated/khan_academy/raw_data/ka_scraper.py
sciphi/deprecated/library_of_phi/gen_step_1_draft_syllabi.py
sciphi/deprecated/library_of_phi/gen_step_2_clean_syllabi.py
sciphi/deprecated/library_of_phi/gen_step_3_draft_table_of_contents.py
sciphi/deprecated/library_of_phi/gen_step_4_clean_table_of_contents.py
sciphi/deprecated/library_of_phi/prompts.py
sciphi/deprecated/library_of_phi/raw_data/ocw_courses.html
sciphi/deprecated/library_of_phi/raw_data/ocw_scraper.py
sciphi/deprecated/makers/__init__.py
sciphi/deprecated/makers/data_maker.py
sciphi/deprecated/populate_chroma/__init__.py
sciphi/deprecated/populate_chroma/runner.py
sciphi/eval/__init__.py
sciphi/eval/base.py
sciphi/eval/rag/__init__.py
sciphi/eval/rag/science_multiple_choice/rag_science_evaluator.py
sciphi/interface/__init__.py
sciphi/interface/base.py
sciphi/interface/llm/__init__.py
sciphi-0.1.7.dist-info/LICENSE
sciphi-0.1.7.dist-info/METADATA
sciphi-0.1.7.dist-info/WHEEL
sciphi-0.1.7.dist-info/RECORD
