Metadata-Version: 2.1
Name: sciphi
Version: 0.1.7
Summary: SciPhi: A Framework for LLM Powered Data.
License: Apache-2.0
Author: Owen Colegrove
Author-email: owen@sciphi.ai
Requires-Python: >=3.9,<3.12
Classifier: License :: OSI Approved :: Apache Software License
Classifier: Programming Language :: Python :: 3
Classifier: Programming Language :: Python :: 3.9
Classifier: Programming Language :: Python :: 3.10
Classifier: Programming Language :: Python :: 3.11
Provides-Extra: all
Provides-Extra: all-with-extras
Provides-Extra: anthropic-support
Provides-Extra: hf-support
Provides-Extra: vllm-support
Requires-Dist: accelerate (>=0.23.0,<0.24.0) ; extra == "hf-support" or extra == "vllm-support" or extra == "all" or extra == "all-with-extras"
Requires-Dist: anthropic (>=0.3.10,<0.4.0) ; extra == "anthropic-support" or extra == "all" or extra == "all-with-extras"
Requires-Dist: blingfire (>=0.1.8,<0.2.0)
Requires-Dist: bs4 (>=0.0.1,<0.0.2)
Requires-Dist: datasets (>=2.14.5,<3.0.0) ; extra == "hf-support" or extra == "all" or extra == "all-with-extras"
Requires-Dist: fire (>=0.5.0,<0.6.0)
Requires-Dist: openai (==0.27.8)
Requires-Dist: pandas (>=2.1.0,<3.0.0)
Requires-Dist: python-dotenv (>=1.0.0,<2.0.0)
Requires-Dist: pyyaml (>=6.0.1,<7.0.0)
Requires-Dist: retrying (>=1.3.4,<2.0.0)
Requires-Dist: sentencepiece (>=0.1.99,<0.2.0)
Requires-Dist: tiktoken (>=0.5.1,<0.6.0)
Requires-Dist: torch (>=2.1.0,<3.0.0) ; extra == "hf-support" or extra == "vllm-support" or extra == "all" or extra == "all-with-extras"
Requires-Dist: tqdm (>=4.66.1,<5.0.0)
Requires-Dist: transformers (>=4.33.1,<5.0.0) ; extra == "hf-support" or extra == "all" or extra == "all-with-extras"
Requires-Dist: vllm (==0.2.0) ; extra == "vllm-support" or extra == "all-with-extras"
